beaver/__init__.py
beaver/blobs.py
beaver/cache.py
beaver/channels.py
beaver/client.py
beaver/collections.py
beaver/core.py
beaver/dicts.py
beaver/lists.py
beaver/locks.py
beaver/logs.py
beaver/manager.py
beaver/queues.py
beaver/server.py
beaver/types.py
beaver/vectors.py
beaver/cli/__init__.py
beaver/cli/blobs.py
beaver/cli/channels.py
beaver/cli/collections.py
beaver/cli/dicts.py
beaver/cli/lists.py
beaver/cli/locks.py
beaver/cli/logs.py
beaver/cli/queues.py
beaver_db-1.0.0.dist-info/METADATA
beaver_db-1.0.0.dist-info/WHEEL
beaver_db-1.0.0.dist-info/entry_points.txt
beaver_db-1.0.0.dist-info/licenses/LICENSE
beaver_db-1.0.0.dist-info/RECORD
