Metadata-Version: 2.4
Name: beaver-db
Version: 1.0.0
Summary: Fast, embedded, and multi-modal DB based on SQLite for AI-powered applications.
License-File: LICENSE
Classifier: License :: OSI Approved :: MIT License
Classifier: Operating System :: OS Independent
Classifier: Programming Language :: Python :: 3.13
Classifier: Topic :: Database
Classifier: Topic :: Software Development :: Libraries :: Application Frameworks
Requires-Python: >=3.13
Requires-Dist: numpy>=2.3.4
Requires-Dist: pydantic>=2.12.3
Requires-Dist: rich>=14.2.0
Requires-Dist: typer>=0.20.0
Provides-Extra: full
Requires-Dist: fastapi[standard]>=0.118.0; extra == 'full'
Provides-Extra: remote
Requires-Dist: fastapi[standard]>=0.118.0; extra == 'remote'
